{
  "Kenya Mobile Safaricom": [
    {
      "prefix": "254110",
      "rate": 0.032
    },
    {
      "prefix": "254111",
      "rate": 0.032
    },
    {
      "prefix": "254112",
      "rate": 0.032
    },
    {
      "prefix": "254113",
      "rate": 0.032
    },
    {
      "prefix": "254114",
      "rate": 0.032
    },
    {
      "prefix": "254115",
      "rate": 0.032
    },
    {
      "prefix": "25470",
      "rate": 0.032
    },
    {
      "prefix": "25471",
      "rate": 0.032
    },
    {
      "prefix": "25472",
      "rate": 0.032
    },
    {
      "prefix": "254740",
      "rate": 0.032
    },
    {
      "prefix": "254741",
      "rate": 0.032
    },
    {
      "prefix": "254742",
      "rate": 0.032
    },
    {
      "prefix": "254743",
      "rate": 0.032
    },
    {
      "prefix": "254745",
      "rate": 0.032
    },
    {
      "prefix": "254746",
      "rate": 0.032
    },
    {
      "prefix": "254748",
      "rate": 0.032
    },
    {
      "prefix": "254757",
      "rate": 0.032
    },
    {
      "prefix": "254758",
      "rate": 0.032
    },
    {
      "prefix": "254759",
      "rate": 0.032
    },
    {
      "prefix": "254768",
      "rate": 0.032
    },
    {
      "prefix": "254769",
      "rate": 0.032
    },
    {
      "prefix": "25479",
      "rate": 0.032
    }
  ],
  "China Mobile": [
    {
      "prefix": "86134",
      "rate": 0.3
    },
    {
      "prefix": "86135",
      "rate": 0.3
    },
    {
      "prefix": "86136",
      "rate": 0.3
    },
    {
      "prefix": "86137",
      "rate": 0.3
    },
    {
      "prefix": "86138",
      "rate": 0.3
    },
    {
      "prefix": "86139",
      "rate": 0.3
    },
    {
      "prefix": "86150",
      "rate": 0.3
    },
    {
      "prefix": "86151",
      "rate": 0.3
    },
    {
      "prefix": "86152",
      "rate": 0.3
    },
    {
      "prefix": "86157",
      "rate": 0.3
    },
    {
      "prefix": "86158",
      "rate": 0.3
    },
    {
      "prefix": "86159",
      "rate": 0.3
    },
    {
      "prefix": "86182",
      "rate": 0.3
    },
    {
      "prefix": "86187",
      "rate": 0.3
    }
  ],
  "China Unicorn": [
    {
      "prefix": "86130",
      "rate": 0.3
    },
    {
      "prefix": "86131",
      "rate": 0.3
    },
    {
      "prefix": "86132",
      "rate": 0.3
    },
    {
      "prefix": "86153",
      "rate": 0.3
    },
    {
      "prefix": "86156",
      "rate": 0.3
    },
    {
      "prefix": "86185",
      "rate": 0.3
    },
    {
      "prefix": "86186",
      "rate": 0.3
    }
  ],
  "China Telecom": [
    {
      "prefix": "86133",
      "rate": 0.3
    },
    {
      "prefix": "86155",
      "rate": 0.3
    },
    {
      "prefix": "86180",
      "rate": 0.3
    },
    {
      "prefix": "86181",
      "rate": 0.3
    },
    {
      "prefix": "86189",
      "rate": 0.3
    }
  ]
}