{
  "Tismi BV": [
    "4915019"
  ],
  "Interactive digital media": [
    "4915020"
  ],
  "NAKA AG": [
    "4915050"
  ],
  "Easy World": [
    "4915080"
  ],
  "T-Mobile": [
    "49151",
    "49160",
    "49170",
    "49171",
    "49175"
  ],
  "Vodafone": [
    "491520",
    "491522",
    "491523",
    "491525",
    "491526",
    "49162",
    "49172",
    "49173",
    "49174"
  ],
  "Vodafone/Lycamobile": [
    "491521"
  ],
  "Vodafone/Truphone": [
    "491529"
  ],
  "Mtel": [
    "491531"
  ],
  "LEBARA": [
    "4915510",
    "4915511"
  ],
  "1&1 Mobilfunk": [
    "491556"
  ],
  "Multiconnect": [
    "4915630"
  ],
  "Argon Networks": [
    "4915678"
  ],
  "Eplus/Telogic": [
    "491570"
  ],
  "Eplus": [
    "491573",
    "491575",
    "491577",
    "491578",
    "49163",
    "49177",
    "49178"
  ],
  "Eplus/Sipgate": [
    "491579"
  ],
  "TelcoVillage": [
    "4915888"
  ],
  "O2": [
    "491590",
    "49176",
    "49179"
  ]
}